setup.py
serverless_runlocal/__init__.py
serverless_runlocal/flask_helper.py
serverless_runlocal/lambda_helper.py
serverless_runlocal/sls_helper.py
serverless_runlocal.egg-info/PKG-INFO
serverless_runlocal.egg-info/SOURCES.txt
serverless_runlocal.egg-info/dependency_links.txt
serverless_runlocal.egg-info/requires.txt
serverless_runlocal.egg-info/top_level.txt