Metadata-Version: 1.0
Name: serverless-runlocal
Version: 0.1.1
Summary: Serverless configuration parser to run your serverless function as Flask.
Home-page: https://github.com/dtak1114/serverless_runlocal
Author: Daisuke Takahashi @dt4k
Author-email: d.takahashi1811@gmail.com
License: MIT
Keywords: serverless aws lambda flask local
Platform: UNKNOWN
